giza/datasets/__init__.py
giza/datasets/cache_manager.py
giza/datasets/constants.py
giza/datasets/defillama_constants.py
giza/datasets/hub.py
giza/datasets/loaders.py
giza/datasets/models.py
giza_datasets-0.3.1.dist-info/LICENSE
giza_datasets-0.3.1.dist-info/METADATA
giza_datasets-0.3.1.dist-info/WHEEL
giza_datasets-0.3.1.dist-info/RECORD
