Metadata-Version: 2.1
Name: giza-datasets
Version: 0.3.1
Summary: 
License: MIT
Author: Fran Algaba
Author-email: f.algaba@outlook.es
Requires-Python: >=3.11,<4.0
Classifier: License :: OSI Approved :: MIT License
Classifier: Programming Language :: Python :: 3
Classifier: Programming Language :: Python :: 3.11
Classifier: Programming Language :: Python :: 3.12
Requires-Dist: gcsfs (>=2023.12.2.post1,<2024.0.0)
Requires-Dist: polars (>=0,<1)
Requires-Dist: pyarrow (>=15,<16)
Requires-Dist: pydantic (>=2,<3)
Requires-Dist: rich (>=13,<14)
